{
  "initTreasuryBridged": 1650839792,
  "initTreasury2": 1650839796,
  "initSnookState": 1650839821,
  "initSnookToken": 1650839825,
  "init3SnookToken": 1650839829,
  "initMarketplaceBridged": 1650839834,
  "initAfterdeathBridged": 1650839844,
  "initSnookGameBridged": 1650839867,
  "init2SnookGame": 1650839877,
  "init3SnookGame": 1650839882,
  "initLuckWheel": 1650839908,
  "initTreasury3": 1650839912,
  "initSnookState2": 1650839916,
  "initBurnSafe": 1650839941,
  "init4SnookGameBridged": 1650839947
}